align/__init__.py
align/kg.py
align/rubbishtest.py
align/sample.py
align/semi_align.py
align/test.py
align/util.py
find_node2merge-0.1.dist-info/METADATA
find_node2merge-0.1.dist-info/WHEEL
find_node2merge-0.1.dist-info/top_level.txt
find_node2merge-0.1.dist-info/RECORD
