Metadata-Version: 2.1
Name: find-node2merge
Version: 0.1
Summary: Find potentially similar nodes in a knowledge graph.
Home-page: UNKNOWN
Author: zsy
License: UNKNOWN
Platform: UNKNOWN
